<?xml version="1.0" encoding="utf-8"?>
<!--NSI Web Service v6.16.0-->
<message:Structure xmlns:message="http://www.sdmx.org/resources/sdmxml/schemas/v2_1/message" xmlns:structure="http://www.sdmx.org/resources/sdmxml/schemas/v2_1/structure" xmlns:common="http://www.sdmx.org/resources/sdmxml/schemas/v2_1/common">
  <message:Header>
    <message:ID>IDREF360</message:ID>
    <message:Test>false</message:Test>
    <message:Prepared>2025-02-14T16:58:26.417925+01:00</message:Prepared>
    <message:Sender id="Unknown" />
    <message:Receiver id="Unknown" />
  </message:Header>
  <message:Structures>
    <structure:Codelists>
      <structure:Codelist id="CL_AREA" urn="urn:sdmx:org.sdmx.infomodel.codelist.Codelist=IT1:CL_AREA(1.2)" agencyID="IT1" version="1.2" isFinal="true">
        <common:Name xml:lang="it">Area</common:Name>
        <common:Name xml:lang="en">Area</common:Name>
        <structure:Code id="SRR" urn="urn:sdmx:org.sdmx.infomodel.codelist.Code=IT1:CL_AREA(1.2).SRR">
          <common:Name xml:lang="it">stessa regione di residenza</common:Name>
          <common:Name xml:lang="en">same region of residence</common:Name>
        </structure:Code>
        <structure:Code id="SPR" urn="urn:sdmx:org.sdmx.infomodel.codelist.Code=IT1:CL_AREA(1.2).SPR">
          <common:Name xml:lang="it">stessa provincia di residenza</common:Name>
          <common:Name xml:lang="en">same province of residence</common:Name>
        </structure:Code>
        <structure:Code id="NSP" urn="urn:sdmx:org.sdmx.infomodel.codelist.Code=IT1:CL_AREA(1.2).NSP">
          <common:Name xml:lang="it">non indicato</common:Name>
          <common:Name xml:lang="en">n.a.</common:Name>
        </structure:Code>
        <structure:Code id="AFFRC" urn="urn:sdmx:org.sdmx.infomodel.codelist.Code=IT1:CL_AREA(1.2).AFFRC">
          <common:Name xml:lang="it">estero di cittadinanza straniera</common:Name>
          <common:Name xml:lang="en">abroad foreigner citizens</common:Name>
        </structure:Code>
        <structure:Code id="ALL" urn="urn:sdmx:org.sdmx.infomodel.codelist.Code=IT1:CL_AREA(1.2).ALL">
          <common:Name xml:lang="it">tutte le voci</common:Name>
          <common:Name xml:lang="en">all items</common:Name>
        </structure:Code>
        <structure:Code id="DR" urn="urn:sdmx:org.sdmx.infomodel.codelist.Code=IT1:CL_AREA(1.2).DR">
          <common:Name xml:lang="it">diversa regione</common:Name>
          <common:Name xml:lang="en">different region</common:Name>
        </structure:Code>
        <structure:Code id="SMR" urn="urn:sdmx:org.sdmx.infomodel.codelist.Code=IT1:CL_AREA(1.2).SMR">
          <common:Name xml:lang="it">stesso comune di residenza</common:Name>
          <common:Name xml:lang="en">same municipality of residence</common:Name>
        </structure:Code>
        <structure:Code id="AFITC" urn="urn:sdmx:org.sdmx.infomodel.codelist.Code=IT1:CL_AREA(1.2).AFITC">
          <common:Name xml:lang="it">estero di cittadinanza italiana</common:Name>
          <common:Name xml:lang="en">abroad Italian citizens</common:Name>
        </structure:Code>
      </structure:Codelist>
    </structure:Codelists>
  </message:Structures>
</message:Structure>